kumpel/__init__.py
kumpel/k_bigquery.py
kumpel-0.11.dist-info/DESCRIPTION.rst
kumpel-0.11.dist-info/METADATA
kumpel-0.11.dist-info/RECORD
kumpel-0.11.dist-info/WHEEL
kumpel-0.11.dist-info/metadata.json
kumpel-0.11.dist-info/top_level.txt
